bodo_platform_dummy_kernel/__init__.py
bodo_platform_dummy_kernel/__main__.py
bodo_platform_dummy_kernel/_version.py
bodo_platform_dummy_kernel/install.py
bodo_platform_dummy_kernel/kernel.py
bodo_platform_dummy_kernel-1.2.0.dist-info/LICENSE
bodo_platform_dummy_kernel-1.2.0.dist-info/METADATA
bodo_platform_dummy_kernel-1.2.0.dist-info/WHEEL
bodo_platform_dummy_kernel-1.2.0.dist-info/top_level.txt
bodo_platform_dummy_kernel-1.2.0.dist-info/RECORD
