Metadata-Version: 2.1
Name: bodo-platform-dummy-kernel
Version: 1.2.0
Summary: A simple wrapper around IPython Kernel for the Bodo Platform Notebook
Home-page: https://github.com/Bodo-inc/bodo-platform-dummy-kernel
Author: Bodo, Inc.
Author-email: noreply@bodo.ai
License: UNKNOWN
Platform: UNKNOWN
Classifier: License :: OSI Approved :: BSD License
Classifier: Programming Language :: Python :: 3
License-File: LICENSE
Requires-Dist: jupyter-client (>=7)
Requires-Dist: ipython (>=7)
Requires-Dist: ipykernel (>=6)
